lt_tensor/__init__.py
lt_tensor/activations_utils.py
lt_tensor/common.py
lt_tensor/display_utils.py
lt_tensor/masking_utils.py
lt_tensor/misc_utils.py
lt_tensor/model_base.py
lt_tensor/monotonic_align.py
lt_tensor/noise_tools.py
lt_tensor/padding_utils.py
lt_tensor/tensor_ops.py
lt_tensor/transform.py
lt_tensor/_misc/_type_hints.py
lt_tensor/_other_ops/__init__.py
lt_tensor/_other_ops/_noise_diffusers.py
lt_tensor/_other_ops/_procedural_noises.py
lt_tensor/_other_ops/torchaudio/cqt_vqt.py
lt_tensor/_other_ops/torchaudio/functional.py
lt_tensor/model_zoo/__init__.py
lt_tensor/model_zoo/basic.py
lt_tensor/model_zoo/conv_norm.py
lt_tensor/model_zoo/convs.py
lt_tensor/model_zoo/diffusion.py
lt_tensor/model_zoo/fusion.py
lt_tensor/model_zoo/pos_encoders.py
lt_tensor/model_zoo/text_encoder.py
lt_tensor/model_zoo/activations/__init__.py
lt_tensor/model_zoo/activations/base.py
lt_tensor/model_zoo/activations/basic_utils.py
lt_tensor/model_zoo/activations/oscillator.py
lt_tensor/model_zoo/activations/trop_set.py
lt_tensor/model_zoo/activations/alias_free/__init__.py
lt_tensor/model_zoo/activations/alias_free/act.py
lt_tensor/model_zoo/activations/alias_free/filter.py
lt_tensor/model_zoo/activations/alias_free/resample.py
lt_tensor/model_zoo/activations/snake/__init__.py
lt_tensor/model_zoo/audio/__init__.py
lt_tensor/model_zoo/audio/features.py
lt_tensor/model_zoo/audio/sine_gen.py
lt_tensor/model_zoo/audio/tts_encoders.py
lt_tensor/model_zoo/audio/vocoders/__init__.py
lt_tensor/model_zoo/audio/vocoders/utils.py
lt_tensor/model_zoo/audio/vocoders/hifigan/__init__.py
lt_tensor/model_zoo/audio/vocoders/hifigan/config.py
lt_tensor/model_zoo/audio/vocoders/hifigan/generator.py
lt_tensor/model_zoo/audio/vocoders/istftnet/__init__.py
lt_tensor/model_zoo/audio/vocoders/istftnet/config.py
lt_tensor/model_zoo/audio/vocoders/istftnet/generator.py
lt_tensor/model_zoo/residual/__init__.py
lt_tensor/model_zoo/residual/amp.py
lt_tensor/model_zoo/residual/basics.py
lt_tensor-0.0.6.0a3.dist-info/licenses/LICENSE
lt_tensor-0.0.6.0a3.dist-info/METADATA
lt_tensor-0.0.6.0a3.dist-info/WHEEL
lt_tensor-0.0.6.0a3.dist-info/top_level.txt
lt_tensor-0.0.6.0a3.dist-info/RECORD
