Metadata-Version: 2.4
Name: lt-tensor
Version: 0.0.6.0a3
Summary: General utilities for PyTorch and others. Built for general use.
Home-page: https://github.com/gr1336/lt-tensor/
Author: gr1336
License: Apache Software License (Apache-2.0)
Classifier: Development Status :: 1 - Planning
Classifier: Topic :: Software Development
Classifier: Topic :: Software Development :: Libraries
Classifier: Topic :: Utilities
License-File: LICENSE
Requires-Dist: torch>=2.6.0
Requires-Dist: torchaudio>=2.6.0
Requires-Dist: numpy>=1.26.4
Requires-Dist: tokenizers
Requires-Dist: pyyaml
Requires-Dist: numba
Requires-Dist: lt-utils>=0.2.0.4
Requires-Dist: librosa<1,>=0.10.2.post1
Requires-Dist: einops
Requires-Dist: plotly
Requires-Dist: scipy
Requires-Dist: typing_extensions
Requires-Dist: optuna
Requires-Dist: tqdm
Dynamic: author
Dynamic: classifier
Dynamic: description
Dynamic: description-content-type
Dynamic: home-page
Dynamic: license
Dynamic: license-file
Dynamic: requires-dist
Dynamic: summary
